toy_glacier/__init__.py
toy_glacier/cli.py
toy_glacier/domain.py
toy_glacier-0.1.1.dist-info/WHEEL
toy_glacier-0.1.1.dist-info/entry_points.txt
toy_glacier-0.1.1.dist-info/METADATA
toy_glacier-0.1.1.dist-info/RECORD
