Metadata-Version: 2.3
Name: toy-glacier
Version: 0.1.1
Summary: This is a toy CLI tool that allows a user to create a 'glacier' and then mimic accumulation & ablation by adding and subtracting mass from it via terminal commands.
Author: Emma Marshall
Author-email: Emma Marshall <emarshall@rhg.com>
Requires-Dist: click>=8.2.1
Requires-Python: >=3.12
